graphicswithpython.py
GraphicswithPython-0.0.11.dist-info/LICENSE.txt
GraphicswithPython-0.0.11.dist-info/METADATA
GraphicswithPython-0.0.11.dist-info/WHEEL
GraphicswithPython-0.0.11.dist-info/top_level.txt
GraphicswithPython-0.0.11.dist-info/RECORD
