Metadata-Version: 2.1
Name: GraphicswithPython
Version: 0.0.11
Summary: Graphic With Python (GWP) is a user-friendly and simpler way to practise and imply Computer Graphic Concept . It is better then graphics.h as GWP is faster & easy to implement. The Aim for this library is to make Computer Graphic Visualization easier and understandable by providing Fuction for each Method and support.
Home-page: https://github.com/YameenV/graphicswithpython.git
Author: Yameen Vinchu, Ashutosh Upadhyay
Author-email: yameenvinchu38@gmail.com, ashutosh.aku.aau@gmail.com
License: UNKNOWN
Platform: UNKNOWN
Classifier: Programming Language :: Python :: 3
Classifier: Programming Language :: Python :: 3.6
Classifier: Programming Language :: Python :: 3.7
Classifier: Development Status :: 3 - Alpha
Classifier: License :: OSI Approved :: Apache Software License
Classifier: Operating System :: OS Independent
License-File: LICENSE.txt
Requires-Dist: pygame (~=2.1.0)
